lt_cvd/__init__.py
lt_cvd/run_model.py
lt_cvd-0.1.0.dist-info/LICENSE
lt_cvd-0.1.0.dist-info/METADATA
lt_cvd-0.1.0.dist-info/WHEEL
lt_cvd-0.1.0.dist-info/entry_points.txt
lt_cvd-0.1.0.dist-info/top_level.txt
lt_cvd-0.1.0.dist-info/RECORD
